bravais/__init__.py
bravais/_version.py
bravais/bravais.py
bravais/utils.py
bravais/valid_parameters.yml
bravais/validator.py
bravais-0.1.4.dist-info/LICENSE
bravais-0.1.4.dist-info/METADATA
bravais-0.1.4.dist-info/WHEEL
bravais-0.1.4.dist-info/top_level.txt
bravais-0.1.4.dist-info/RECORD
