Metadata-Version: 2.1
Name: bravais
Version: 0.1.4
Summary: A simple package for representing Bravais lattices. Primarily useful to check the passed parameters represent a valid Bravais lattice.
Home-page: UNKNOWN
Author: Adam J. Plowman, Maria S. Yankova
License: UNKNOWN
Project-URL: Github, https://github.com/aplowman/bravais
Platform: UNKNOWN
Classifier: Development Status :: 4 - Beta
Classifier: Topic :: Scientific/Engineering :: Physics
Classifier: Intended Audience :: Developers
Classifier: Intended Audience :: Science/Research
Classifier: Programming Language :: Python :: 3.5
Classifier: Programming Language :: Python :: 3.6
Classifier: Programming Language :: Python :: 3.7
Classifier: Operating System :: OS Independent
Classifier: License :: OSI Approved :: Mozilla Public License 2.0 (MPL 2.0)
Requires-Dist: numpy
Requires-Dist: pyyaml
